nomad_camels_driver_rhode_and_schwarz_smp_02/rhode_and_schwarz_smp_02.py
nomad_camels_driver_rhode_and_schwarz_smp_02/rhode_and_schwarz_smp_02_ophyd.py
nomad_camels_driver_rhode_and_schwarz_smp_02-0.1.0.dist-info/LICENSE.txt
nomad_camels_driver_rhode_and_schwarz_smp_02-0.1.0.dist-info/METADATA
nomad_camels_driver_rhode_and_schwarz_smp_02-0.1.0.dist-info/WHEEL
nomad_camels_driver_rhode_and_schwarz_smp_02-0.1.0.dist-info/top_level.txt
nomad_camels_driver_rhode_and_schwarz_smp_02-0.1.0.dist-info/RECORD
